cairogen/__init__.py
cairogen/grids/__init__.py
cairogen/grids/delaunay.py
cairogen/grids/grid.py
cairogen/grids/gridQuad.py
cairogen/grids/voronoi.py
cairogen/helpers/__init__.py
cairogen/helpers/helpers.py
cairogen/lines/__init__.py
cairogen/lines/line.py
cairogen/lines/segment.py
cairogen/particles/__init__.py
cairogen/particles/particle.py
cairogen/polys/__init__.py
cairogen/polys/carre.py
cairogen/polys/poly.py
cairogen-0.1.dist-info/METADATA
cairogen-0.1.dist-info/WHEEL
cairogen-0.1.dist-info/top_level.txt
cairogen-0.1.dist-info/RECORD
